llama_index/llms/deepinfra/__init__.py
llama_index/llms/deepinfra/base.py
llama_index/llms/deepinfra/client.py
llama_index/llms/deepinfra/constants.py
llama_index/llms/deepinfra/types.py
llama_index/llms/deepinfra/utils.py
llama_index_llms_deepinfra-0.5.2.dist-info/METADATA
llama_index_llms_deepinfra-0.5.2.dist-info/WHEEL
llama_index_llms_deepinfra-0.5.2.dist-info/licenses/LICENSE
llama_index_llms_deepinfra-0.5.2.dist-info/RECORD
