Metadata-Version: 2.4
Name: llama-index-llms-deepinfra
Version: 0.5.2
Summary: llama-index llms deepinfra integration
Author-email: Oguz Vuruskaneer <oguzvuruskaner@gmail.com>
License-Expression: MIT
License-File: LICENSE
Requires-Python: <4.0,>=3.9
Requires-Dist: aiohttp<4,>=3.8.1
Requires-Dist: llama-index-core<0.15,>=0.14.3
Requires-Dist: llama-index-llms-openai<0.7,>=0.6.0
Requires-Dist: tenacity<8.4.0,>=8.1.0
